Metadata-Version: 2.1
Name: twstock-downloader
Version: 0.1.1
Summary: daily taiwan stock price downloader
Home-page: https://github.com/TwQin0403/twstock_downloader
Author: Qin Wei Zhi
Author-email: p300053000qin@gmail.com
License: Copyright (c) 2020, Qin,Wei-Zhi
